fulcrum/__init__.py
fulcrum/client.py
fulcrum/bridge/__init__.py
fulcrum/bridge/v1/__init__.py
fulcrum/bridge/v1/bridge_pb2.py
fulcrum/bridge/v1/bridge_pb2.pyi
fulcrum/bridge/v1/bridge_pb2_grpc.py
fulcrum/checkpoint/__init__.py
fulcrum/checkpoint/v1/__init__.py
fulcrum/checkpoint/v1/checkpoint_service_pb2.py
fulcrum/checkpoint/v1/checkpoint_service_pb2.pyi
fulcrum/checkpoint/v1/checkpoint_service_pb2_grpc.py
fulcrum/cost/__init__.py
fulcrum/cost/v1/__init__.py
fulcrum/cost/v1/cost_service_pb2.py
fulcrum/cost/v1/cost_service_pb2.pyi
fulcrum/cost/v1/cost_service_pb2_grpc.py
fulcrum/envelope/v1/envelope_pb2.py
fulcrum/envelope/v1/envelope_pb2.pyi
fulcrum/envelope/v1/envelope_pb2_grpc.py
fulcrum/envelope/v1/envelope_service_pb2.py
fulcrum/envelope/v1/envelope_service_pb2.pyi
fulcrum/envelope/v1/envelope_service_pb2_grpc.py
fulcrum/events/v1/events_pb2.py
fulcrum/events/v1/events_pb2.pyi
fulcrum/events/v1/events_pb2_grpc.py
fulcrum/eventstore/__init__.py
fulcrum/eventstore/v1/__init__.py
fulcrum/eventstore/v1/eventstore_pb2.py
fulcrum/eventstore/v1/eventstore_pb2.pyi
fulcrum/eventstore/v1/eventstore_pb2_grpc.py
fulcrum/policy/__init__.py
fulcrum/policy/v1/__init__.py
fulcrum/policy/v1/policy_service_pb2.py
fulcrum/policy/v1/policy_service_pb2.pyi
fulcrum/policy/v1/policy_service_pb2_grpc.py
fulcrum/tenant/v1/tenant_service_pb2.py
fulcrum/tenant/v1/tenant_service_pb2.pyi
fulcrum/tenant/v1/tenant_service_pb2_grpc.py
fulcrum/v1/__init__.py
fulcrum_governance-0.1.1.dist-info/licenses/LICENSE
fulcrum_governance-0.1.1.dist-info/METADATA
fulcrum_governance-0.1.1.dist-info/WHEEL
fulcrum_governance-0.1.1.dist-info/top_level.txt
fulcrum_governance-0.1.1.dist-info/RECORD
