Metadata-Version: 2.4
Name: fulcrum-governance
Version: 0.1.1
Summary: Python SDK for Fulcrum - Intelligent AI Governance Platform
Author-email: Fulcrum Team <hello@fulcrum.dev>
License-Expression: Apache-2.0
Project-URL: Homepage, https://fulcrum.dev
Project-URL: Documentation, https://docs.fulcrum.dev
Project-URL: Repository, https://github.com/fulcrum-io/fulcrum
Project-URL: Changelog, https://github.com/fulcrum-io/fulcrum/blob/main/CHANGELOG.md
Keywords: ai,governance,llm,agents,safety,compliance
Classifier: Development Status :: 4 - Beta
Classifier: Intended Audience :: Developers
Classifier: Programming Language :: Python :: 3
Classifier: Programming Language :: Python :: 3.9
Classifier: Programming Language :: Python :: 3.10
Classifier: Programming Language :: Python :: 3.11
Classifier: Programming Language :: Python :: 3.12
Classifier: Topic :: Software Development :: Libraries :: Python Modules
Classifier: Topic :: Scientific/Engineering :: Artificial Intelligence
Requires-Python: >=3.9
License-File: LICENSE
Requires-Dist: grpcio>=1.60.0
Requires-Dist: protobuf>=4.25.0
Requires-Dist: googleapis-common-protos>=1.60.0
Provides-Extra: dev
Requires-Dist: grpcio-tools>=1.60.0; extra == "dev"
Requires-Dist: pytest>=7.0; extra == "dev"
Requires-Dist: pytest-asyncio>=0.21; extra == "dev"
Requires-Dist: black; extra == "dev"
Requires-Dist: mypy; extra == "dev"
Requires-Dist: ruff; extra == "dev"
Dynamic: license-file
